{"Facilty Title":{"0":"Seegehalli","1":"PHC Manduru","2":"Marathalli","3":"Bidarahalli","4":"HALANAYAKANAHALLI","5":"Kannuru","6":"H.AGARA","7":"Hoodi","8":"VARTHURU 24X7 UPHC","9":"SORHUNSE","10":"BANGALORE EAST TALUK HOSPITAL","11":"k.R.pura","12":"MAHADEVAPURA","13":"MULLURU","14":"Whitefield","15":"GARUDACHARAPALYA","16":"Varthuru","17":"KADUSONNAPPANAHALLI","18":"SIDDAPURA UPHC","19":"BANGALORE EAST TH","20":"BELANDUR","21":"KADUGODI 24X7 UPHC","22":"Witefield","23":"Immadihalli","24":"Siddapura","25":"KODATHI","26":"Dasarahalli","27":"ISLAMPURA","28":"K NARAYANAPURA UPHC","29":"Bidarahalli","30":"Kaidenahalli","31":"KAIKONDRAHALLI","32":"KANNAMANGALA","33":"DODDAKANNALLI","34":"Avalahalli","35":"Avalahalli","36":"RAMGONDANHALLI","37":"Yamaluru","38":"Medahalli","39":"MARATHAHALLI","40":"DOODDANEKKUNDI 24X7 UPHC","41":"VIBUTHIPURA UPHC","42":"MANDUR","43":"K R PURA","44":"VARTHUR","45":"MANJUNATHANAGARA","46":"Kadugodi","47":"B NARAYANAPURA","48":"GOTTIGERE UPHC","49":"CHANNASANDRA","50":"K.NARAYANAPURA","51":"Vijanapura","52":"THANISANDRA","53":"DODDANEKKUNDI","54":"YAMLURU UPHC","55":"Gunjuru","56":"Doddagubbi","57":"Horamavu","58":"Panathuru","59":"Vibutipura","60":"DODDAKANNALLI UPHC","61":"PATALAMMA BADAVANI","62":"GUNJURU UPHC"},"Health Facility Name":{"0":"Seegehalli  Metarnity Hospital","1":"PHC Manduru","2":"PHC Marathalli","3":"PHC Bidarahalli","4":"PHC HALANAYAKANAHALLI","5":"PHC Kannuru","6":"H Hagara Subcentre","7":"Subcentre Hoodi","8":"Primary Health Center,","9":"Subcentre Soravunase","10":"K.R.Pura Genaral Hospital","11":"Primary Health Center,","12":"Subcentre Mahadevpura","13":"Subcentre Malluru","14":"Subcentre Whitefield","15":"Garudacharpalya","16":"Subcentre Varthuru","17":"Subcentre K.S.Halli","18":"Primary Health Center,","19":"K.R.Pura Genaral Hospital","20":"Subcentre Bellanduru","21":"Primary Health Center,","22":"Subcentre Witefield","23":"Immadihalli","24":"Subcentre Siddapura","25":"PHC Kodathi","26":"Subcentre Dasarahalli","27":"Subcentre Isalampura","28":"Primary Health Center,","29":"Subcentre Bidarahalli","30":"Kaidenahalli Subcentre","31":"Kaikonrrdrahalli Subcentre","32":"Subcentre Kannamagala","33":"Subcentre Doddakannahalli","34":"CHC Avalahalli","35":"Avalahalli","36":"Subcentre Ramagondanahalli","37":"Yamaluru","38":"Subcentre Medahalli","39":"Subcentre Marthahalli","40":"Primary Health Center,","41":"Primary Health Center,","42":"Subcentre Manduru","43":"Sub centre K R Puram","44":"Subcentre Varthuru","45":"Subcentre Manjunatha nagara","46":"Sub centre Kadugodi","47":"Subcentre B.Narayanapura","48":"Gottigere","49":"Channasandra","50":"Subcentre K.Narayanapura","51":"Primary Health Center,","52":"Subcentre Thnisandra","53":"Subcentre Doddanekundi","54":"Primary Health Center,","55":"Primary Health Center,","56":"Subcentre Doddagubbi","57":"Subcentre Horamavu","58":"Panathuru Subcentre","59":null,"60":"Primary Health Center,","61":"Sub Center Patalamma badavane,","62":"Primary Health Center,"},"Address":{"0":"Virgonagara Post","1":"Manduru","2":"CHOWDISHWARI LAYOUT","3":"Bidarahalli","4":"HALANAYAKANAHALLI post","5":"Kannuru","6":"H Hagara","7":null,"8":"Varthuru  Varthuru Post","9":null,"10":"Old Madras road","11":"K.R.Pura Genaral Hospital","12":null,"13":"Malluru","14":null,"15":"Subcentre","16":"VARTHURU","17":"K.S.Halli","18":"Siddapura HAL Road","19":null,"20":null,"21":"Primary Health Center,","22":null,"23":"Immedihalli","24":null,"25":"Carmelaram post","26":"Dasarahalli","27":"Isalampura","28":"K. Narayanapura","29":null,"30":null,"31":"Bellandur","32":"Kannamagala","33":null,"34":"Old Madars road","35":null,"36":"Ramagondanahalli","37":"Subcentre","38":"Medahalli","39":"Marathalli","40":"Doddnekundi","41":"VIBUTHIPURA","42":null,"43":"Old Madras road","44":null,"45":null,"46":null,"47":null,"48":"BANNERUGHATTA MAIN ROAD","49":null,"50":"K.Narayanapura","51":"K.R.Pura Genaral Hospital","52":null,"53":"Marathalli","54":"Yamaluru","55":"Gunjuru Varthuru Hobali","56":"Doddagubbi","57":"Horamavu","58":null,"59":null,"60":"Doddakannahalli","61":"KADUGODI PHC","62":"Gunjuru Varthuru Hobali"},"Location":{"0":"Seegehalli","1":"Manduru","2":"Marathalli","3":"Bidarahalli","4":"HALANAYAKANAHALLI","5":"Kannuru","6":"K Narayanapura","7":"Old madras road, K.R Puram","8":"Varthuru main Road","9":"Varthuru Hobli","10":"K.R.Pura","11":"K.R.Pura Bangalore 36","12":"Doddanekundi","13":"Kodathi","14":"Varthuru","15":"Doddanekundi","16":"VARTHURU","17":"K.S.Halli","18":"Siddapura HAL Road","19":"K.R.Pura","20":"Bellanduru road","21":"Kadugodi Whit Filed Road","22":"Whitefield  road","23":"VARTHURU","24":"Siddapura HAL Road","25":"Kodathi","26":"K Narayanapura","27":"vibhuthipura","28":"Kottanur Post","29":"Bidarahalli","30":"K.R.Pura Bangalore 36","31":"Sarjapur Road","32":"Avalahalli","33":"Doddakannahalli","34":"Virgonagar Post","35":"Avalahalli","36":"Siddapura HAL Road","37":"Yamaluru","38":"Kadugodi","39":"Marthahalli","40":"marathalli Post","41":"Vibthutipura","42":"Manduru","43":"K.R.Pura","44":"Varthuru","45":"Ramamurthy nagar","46":"Kadugodi","47":"K R puram","48":"MAIN ROAD","49":"Kadugodi","50":"K Narayanapura","51":"K.R.Pura Bangalore 36","52":"K Narayanapura","53":"Marthahalli","54":"Yamaluru","55":"Gunjuru Post","56":"Kannuru","57":"K Narayanapura","58":"Panathuru","59":"Vibutipura","60":"Carmelram Post","61":"Kadugodi Whit Filed Road","62":"Gunjuru Post"},"Pincode":{"0":560049.0,"1":560037.0,"2":560035.0,"3":560049.0,"4":560035.0,"5":370035.0,"6":560077.0,"7":560048.0,"8":560087.0,"9":560087.0,"10":560036.0,"11":560036.0,"12":560037.0,"13":560035.0,"14":560087.0,"15":560048.0,"16":560087.0,"17":560094.0,"18":560066.0,"19":560036.0,"20":560103.0,"21":560067.0,"22":560066.0,"23":560087.0,"24":560066.0,"25":560035.0,"26":560077.0,"27":560037.0,"28":560077.0,"29":560049.0,"30":560036.0,"31":560035.0,"32":560049.0,"33":560035.0,"34":560049.0,"35":560049.0,"36":null,"37":null,"38":560067.0,"39":560037.0,"40":560037.0,"41":560037.0,"42":560037.0,"43":560036.0,"44":560087.0,"45":560026.0,"46":560067.0,"47":560077.0,"48":560083.0,"49":560067.0,"50":560077.0,"51":560036.0,"52":560077.0,"53":560037.0,"54":560037.0,"55":560078.0,"56":350035.0,"57":560077.0,"58":560103.0,"59":560037.0,"60":560035.0,"61":560067.0,"62":560087.0}}